LICENSE
README.md
pyproject.toml
txhttputil/__init__.py
txhttputil.egg-info/PKG-INFO
txhttputil.egg-info/SOURCES.txt
txhttputil.egg-info/dependency_links.txt
txhttputil.egg-info/requires.txt
txhttputil.egg-info/top_level.txt
txhttputil/downloader/HttpFileDownloader.py
txhttputil/downloader/HttpResourceProxy.py
txhttputil/downloader/__init__.py
txhttputil/login_page/LoginElement.py
txhttputil/login_page/LoginTemplate.xml
txhttputil/login_page/__init__.py
txhttputil/site/AuthCredentials.py
txhttputil/site/AuthResource.py
txhttputil/site/AuthSessionWrapper.py
txhttputil/site/AuthUserDetails.py
txhttputil/site/BasicResource.py
txhttputil/site/BasicResourceTest.py
txhttputil/site/FileUnderlayResource.py
txhttputil/site/FileUnderlayResourceTest.py
txhttputil/site/FileUploadRequest.py
txhttputil/site/RedirectToHttpsResource.py
txhttputil/site/RedirectionRule.py
txhttputil/site/ResourceCreator.py
txhttputil/site/RootResource.py
txhttputil/site/RootSiteTest.py
txhttputil/site/SiteUtil.py
txhttputil/site/StaticFileResource.py
txhttputil/site/__init__.py
txhttputil/util/DeferUtil.py
txhttputil/util/ModuleUtil.py
txhttputil/util/PemUtil.py
txhttputil/util/SslUtil.py
txhttputil/util/__init__.py