Metadata-Version: 2.1
Name: txhttputil
Version: 1.4.8
Summary: Synerty utility classes for serving a static site with twisted.web with user permissions.
Author-email: Synerty <contact@synerty.com>
Project-URL: Homepage, https://gitlab.synerty.com/peek/util/txhttputil
Keywords: twisted,resource,file,download,synerty
Classifier: Programming Language :: Python :: 3.9
Classifier: Programming Language :: Python :: 3.10
Classifier: Programming Language :: Python :: 3.11
Classifier: Programming Language :: Python :: 3.12
Requires-Python: >=3.9
License-File: LICENSE
Requires-Dist: pytz
Requires-Dist: txwebsocket>=1.0.1
Requires-Dist: filetype
Requires-Dist: pem
Requires-Dist: pytmpdir
Requires-Dist: treelib>=1.6.4
Requires-Dist: cryptography
Requires-Dist: pyOpenSSL
